covplan/__init__.py
covplan/convert_coordinates.py
covplan/coverage_path_planner.py
covplan/dubins_path_planner.py
covplan/field.py
covplan/lines.py
covplan-0.2.0.dist-info/LICENSE
covplan-0.2.0.dist-info/METADATA
covplan-0.2.0.dist-info/WHEEL
covplan-0.2.0.dist-info/top_level.txt
covplan-0.2.0.dist-info/RECORD
