Metadata-Version: 2.1
Name: covplan
Version: 0.2.0
Summary: A package to generate a guidance trajectory for complete 2D coverage of a region of interest
Author-email: "Sanjeev Kumar R. S." <sanjeev.k.r.sudha@ntnu.no>, "Ibrahim A. Hameed" <ibib@ntnu.no>
Project-URL: Homepage, https://github.com/sanjeevrs2000/cpp
Project-URL: Bug Tracker, https://github.com/sanjeevrs2000/cpp/issues
Classifier: Programming Language :: Python :: 3
Classifier: License :: OSI Approved :: MIT License
Classifier: Operating System :: OS Independent
Requires-Python: >=3.7
License-File: LICENSE
Requires-Dist: matplotlib ~=3.6
Requires-Dist: scipy >=1.10
Requires-Dist: scikit-learn >=1.2.0
Requires-Dist: wheel
Requires-Dist: utm
Requires-Dist: folium
Requires-Dist: python-tsp >=0.3
